inclusive/__init__.py
inclusive/inclusive.py
inclusive/tests/__init__.py
inclusive/tests/test_inclusive.py
inclusive-0.0.2.dist-info/LICENSE
inclusive-0.0.2.dist-info/METADATA
inclusive-0.0.2.dist-info/WHEEL
inclusive-0.0.2.dist-info/top_level.txt
inclusive-0.0.2.dist-info/RECORD
