Metadata-Version: 2.1
Name: inclusive
Version: 0.0.2
Summary: Inclusive range and slice
Home-page: https://github.com/numpde/inclusive
Author: RA
Author-email: numpde@null.net
License: UNKNOWN
Keywords: development range slice
Platform: UNKNOWN
Classifier: Intended Audience :: Developers
Classifier: Programming Language :: Python :: 3
Classifier: License :: OSI Approved :: MIT License
Classifier: Operating System :: OS Independent
Requires-Python: >=3.6
